README.md
setup.cfg
setup.py
fancy_text/__init__.py
fancy_text/fancy_text.py
fancy_text.egg-info/PKG-INFO
fancy_text.egg-info/SOURCES.txt
fancy_text.egg-info/dependency_links.txt
fancy_text.egg-info/top_level.txt