Metadata-Version: 1.0
Name: fancy-text
Version: 2.1
Summary: Generate fancy text
Home-page: https://github.com/nitanmarcel/fancy_text
Author: Marcel Alexandru Nitan
Author-email: nitan.marcel@gmail.com
License: MIT
Platform: UNKNOWN
